footium_api/__init__.py
footium_api/cached_gql_connection.py
footium_api/gql_connection.py
footium_api/key_signer.py
footium_api/report.py
footium_api/mutations/__init__.py
footium_api/mutations/lineups.py
footium_api/mutations/player_assignment.py
footium_api/mutations/training_slots.py
footium_api/queries/__init__.py
footium_api/queries/all_clubs_basic_info.py
footium_api/queries/club_tournaments.py
footium_api/queries/fixtures.py
footium_api/queries/formations.py
footium_api/queries/lineups.py
footium_api/queries/players.py
footium_api/queries/server_metadata.py
footium_api/queries/training_slots.py
footium_api-0.1.10.dist-info/licenses/LICENSE
footium_api-0.1.10.dist-info/METADATA
footium_api-0.1.10.dist-info/WHEEL
footium_api-0.1.10.dist-info/top_level.txt
footium_api-0.1.10.dist-info/RECORD
